funny_passphrase/__init__.py
funny_passphrase/__main__.py
funny_passphrase/generator.py
funny_passphrase/py.typed
funny_passphrase/indexer/__init__.py
funny_passphrase/indexer/__main__.py
funny_passphrase-0.2.3.dist-info/LICENSE
funny_passphrase-0.2.3.dist-info/METADATA
funny_passphrase-0.2.3.dist-info/WHEEL
funny_passphrase-0.2.3.dist-info/entry_points.txt
funny_passphrase-0.2.3.dist-info/top_level.txt
funny_passphrase-0.2.3.dist-info/RECORD
