Metadata-Version: 2.1
Name: funny-passphrase
Version: 0.2.3
Summary: A library to index text files, and generate passphrases from them
Home-page: https://github.com/inab/funny-passphrase
Author: José M. Fernández <https://orcid.org/0000-0002-4806-5140>
Author-email: jose.m.fernandez@bsc.es
License: LGPL-2.1
Project-URL: Bug Tracker, https://github.com/inab/funny-passphrase/issues
Classifier: Programming Language :: Python :: 3
Classifier: Development Status :: 3 - Alpha
Classifier: License :: OSI Approved :: GNU Lesser General Public License v2 or later (LGPLv2+)
Classifier: Operating System :: OS Independent
Requires-Python: >=3.6
License-File: LICENSE
Requires-Dist: python-xz
Requires-Dist: typing-extensions
Requires-Dist: python-magic
